qbeast/__init__.py
qbeast/config.py
qbeast/main.py
qbeast/predefs.py
qbeast/utils.py
qbeast/auth/__init__.py
qbeast/auth/auth.py
qbeast/auth/commands.py
qbeast/curator/__init__.py
qbeast/curator/api.py
qbeast/curator/commands.py
qbeast/curator/deployment.py
qbeast/curator/project.py
qbeast/curator/run.py
qbeast/curator/snapshot.py
qbeast/curator/test.py
qbeast/curator/utils.py
qbeast/expo/__init__.py
qbeast/expo/commands.py
qbeast/expo/expo.py
qbeast/tests/__init__.py
qbeast/tests/test_auth.py
qbeast_cli-0.2.0.dist-info/METADATA
qbeast_cli-0.2.0.dist-info/WHEEL
qbeast_cli-0.2.0.dist-info/entry_points.txt
qbeast_cli-0.2.0.dist-info/top_level.txt
qbeast_cli-0.2.0.dist-info/RECORD
