Metadata-Version: 2.1
Name: qbeast-cli
Version: 0.2.0
Summary: A command line interface for the Qbeast services
Author: Qbeast
Classifier: Programming Language :: Python :: 3
Requires-Dist: click (==8.1.3)
Requires-Dist: requests (==2.27.1)
Requires-Dist: tabulate (==0.9.0)
Requires-Dist: PyYAML (==6.0)
